{
 "argv": [
  "/usr/bin/python2.7",
  "-m",
  "ipykernel",
  "-f",
  "{connection_file}"
 ],
 "language": "python",
 "display_name": "PySpark (Python-2.7 / Spark ) [CLUSTER]",
 "env": {
  "HADOOP_CONF_DIR" : "/srv/hadoopconf/config/CLUSTER",
  "YARN_CONF_DIR": "/srv/hadoopconf/config/CLUSTER",
  "PYSPARK_PYTHON": "python2.7",
  "SPARK_HOME": "/opt/spark/",
  "PYTHONPATH": "/opt/spark/python/lib/py4j-0.9-src.zip:/opt/spark/python/:",
  "PYTHONSTARTUP": "/opt/spark/python/pyspark/shell.py",
  "PYSPARK_SUBMIT_ARGS": "--master yarn pyspark-shell"
 }
}